aroleid_simple_strategy_prototyper/__init__.py
aroleid_simple_strategy_prototyper/backtester.py
aroleid_simple_strategy_prototyper/helpers.py
aroleid_simple_strategy_prototyper-0.2.0.dist-info/LICENSE
aroleid_simple_strategy_prototyper-0.2.0.dist-info/METADATA
aroleid_simple_strategy_prototyper-0.2.0.dist-info/WHEEL
aroleid_simple_strategy_prototyper-0.2.0.dist-info/RECORD
