Metadata-Version: 2.3
Name: aroleid-simple-strategy-prototyper
Version: 0.2.0
Summary: A Python package for backtesting trading strategies with OHLCV data
License: GNU GPL v3.0
Author: Nils P. Kujath
Author-email: 63961429+NilsKujath@users.noreply.github.com
Requires-Python: >=3.11
Classifier: License :: OSI Approved :: GNU General Public License v3 (GPLv3)
Classifier: Programming Language :: Python :: 3.11
Classifier: Development Status :: 2 - Pre-Alpha
Classifier: Operating System :: OS Independent
Classifier: Intended Audience :: Developers
Requires-Dist: matplotlib (>=3.10.3,<4.0.0)
Requires-Dist: pandas (>=2.2.3,<3.0.0)
Project-URL: Bug Tracker, https://github.com/nilskujath/aroleid_simple_strategy_prototyper/issues
Project-URL: Homepage, https://github.com/nilskujath/aroleid_simple_strategy_prototyper
